petromodder/__init__.py
petromodder/base_model.py
petromodder/cultural_data.py
petromodder/lithology.py
petromodder/logging.py
petromodder/model3D.py
petromodder/models.py
petromodder/project.py
petromodder/project_data.py
petromodder/utils.py
petromodder-0.1.2.dist-info/LICENSE.md
petromodder-0.1.2.dist-info/METADATA
petromodder-0.1.2.dist-info/WHEEL
petromodder-0.1.2.dist-info/top_level.txt
petromodder-0.1.2.dist-info/RECORD
