Metadata-Version: 2.1
Name: petromodder
Version: 0.1.2
Summary: Tools for manupulating PetroMod model
Home-page: https://github.com/equinor/petromodder
Author: Adam Cheng
Author-email: tkc@equinor.com
Project-URL: Documentation, https://equinor.github.io/petromodder/
Project-URL: Issue Tracker, https://github.com/equinor/petromodder/issues
Classifier: Programming Language :: Python :: 3
Classifier: License :: OSI Approved :: GNU Lesser General Public License v3 or later (LGPLv3+)
Classifier: Operating System :: OS Independent
Requires-Python: >=3.7,>=3.8,>=3.9,>=3.10
License-File: LICENSE.md
Requires-Dist: pandas (>=1.0.0)
Requires-Dist: shapely (>=1.6.3)
Requires-Dist: tabulate (>=0.8.3)
Requires-Dist: xtgeo (>=2.14.1)
